postcodepy/__init__.py
postcodepy/postcodepy.py
postcodepy/typedefs.py
tests/__init__.py
tests/test_adres_api.py
tests/test_signal_api.py
tests/unittestsetup.py
postcodepy-1.2.0.dist-info/LICENSE
postcodepy-1.2.0.dist-info/METADATA
postcodepy-1.2.0.dist-info/WHEEL
postcodepy-1.2.0.dist-info/top_level.txt
postcodepy-1.2.0.dist-info/RECORD
