Metadata-Version: 2.1
Name: postcodepy
Version: 1.2.0
Summary: API-wrapper for postcode.nl REST-API to retrieve relevant address information based on 'postal code', or in Dutch: postcode/huisnummer
Home-page: https://github.com/hootnot/postcode-api-wrapper
Author: Feite Brekeveld
Author-email: f.brekeveld@gmail.com
License: MIT
Keywords: postcode.nl REST API wrapper python
Platform: UNKNOWN
Classifier: Development Status :: 5 - Production/Stable
Classifier: Intended Audience :: Developers
Classifier: Programming Language :: Python :: 3.5
Classifier: Programming Language :: Python :: 3.6
Classifier: Programming Language :: Python :: 3.7
Classifier: Programming Language :: Python :: 3.8
Classifier: Topic :: Utilities
